jsonio/__init__.py
jsonio/handlers.py
jsonio/main.py
jsonio-0.1.4.dist-info/LICENSE.txt
jsonio-0.1.4.dist-info/METADATA
jsonio-0.1.4.dist-info/RECORD
jsonio-0.1.4.dist-info/WHEEL
jsonio-0.1.4.dist-info/top_level.txt
