Metadata-Version: 2.1
Name: jsonio
Version: 0.1.4
Summary: JSON Helpers
Home-page: https://github.com/ylathouris/jsonio
Author: Yani Lathouris
Author-email: ylathouris@gmail.com
License: MIT
Project-URL: Source, https://github.com/ylathouris/jsonio
Project-URL: Tracker, https://github.com/ylathouris/jsonio/issues
Project-URL: Say Thanks!, http://saythanks.io/to/ylathouris
Keywords: jsonio,json,utils
Platform: UNKNOWN
Classifier: Development Status :: 3 - Alpha
Classifier: Intended Audience :: Developers
Classifier: Topic :: Software Development :: Build Tools
Classifier: License :: OSI Approved :: MIT License
Classifier: Programming Language :: Python :: 2.7
Classifier: Programming Language :: Python :: 3.3
Classifier: Programming Language :: Python :: 3.4
Classifier: Programming Language :: Python :: 3.5
Classifier: Programming Language :: Python :: 3.6
Classifier: Programming Language :: Python :: 3.7
Requires-Python: >=2.6, !=3.0.*, !=3.1.*, !=3.2.*, <4
Requires-Dist: python-dateutil (<3,>=2.7.5)
